cello/__init__.py
cello/cello.py
cello/cello_predict.py
cello/cello_quantify_sample.py
cello/cello_train_model.py
cello/download_kallisto_reference.py
cello/download_resources.py
cello/load_expression_matrix.py
cello/load_training_data.py
cello/ontology_utils.py
cello/plot_annotations.py
cello/scanpy_cello.py
cello/the_ontology.py
cello/graph_lib/__init__.py
cello/graph_lib/graph.py
cello/models/__init__.py
cello/models/binary_classifier.py
cello/models/cascaded_discriminative_classifiers.py
cello/models/ensemble_binary_classifiers.py
cello/models/isotonic_regression.py
cello/models/model.py
cello/models/model_utils.py
cello/models/one_nn.py
cello/models/pca.py
cello/models/scale.py
cello/onto_lib_py3/__init__.py
cello/onto_lib_py3/config.py
cello/onto_lib_py3/general_ontology_tools.py
cello/onto_lib_py3/load_ontology.py
cello/onto_lib_py3/ont_prefix_to_filename.json
cello/onto_lib_py3/ontology_configurations.json
cello/onto_lib_py3/ontology_graph.py
cello/onto_lib_py3/metadata/term_to_extra_synonyms.json
cello/onto_lib_py3/metadata/term_to_remove_synonyms.json
cello/onto_lib_py3/obo/CL.18-11-13.obo
cello/onto_lib_py3/obo/CVCL.17-01-30.obo
cello/onto_lib_py3/obo/DOID.17-01-30.obo
cello/onto_lib_py3/obo/EFO.17-01-30.obo
cello/onto_lib_py3/obo/UBERON.17-01-30.obo
cello/onto_lib_py3/obo/cellosaurus.2-29-16.obo
cello_classify-2.1.1.dist-info/LICENSE
cello_classify-2.1.1.dist-info/METADATA
cello_classify-2.1.1.dist-info/WHEEL
cello_classify-2.1.1.dist-info/entry_points.txt
cello_classify-2.1.1.dist-info/top_level.txt
cello_classify-2.1.1.dist-info/zip-safe
cello_classify-2.1.1.dist-info/RECORD
